pyGit/__init__.py
pyyGit-0.3.1.dist-info/LICENCE
pyyGit-0.3.1.dist-info/METADATA
pyyGit-0.3.1.dist-info/WHEEL
pyyGit-0.3.1.dist-info/top_level.txt
pyyGit-0.3.1.dist-info/RECORD
