Metadata-Version: 2.1
Name: pyyGit
Version: 0.3.1
Summary: the missing Python git module
Home-page: https://github.com/TheTechRobo/PyGit
Author: TheTechRobo
Author-email: thetechrobo@outlook.com
License: DBAD
Project-URL: Documentation, https://github.com/thetechrobo/PyGit/wiki
Project-URL: Source, https://github.com/thetechrobo/pygit
Project-URL: Tracker, https://github.com/thetechrobo/pygit/issues
Keywords: git,easy,thetechrobo
Platform: UNKNOWN
Classifier: Development Status :: 3 - Alpha
Classifier: Intended Audience :: Developers
Classifier: Programming Language :: Python :: 3
Requires-Python: >=3
